{
  "lexus_is300_1999_2005": {
    "models": ["IS300","IS 300","IS-300","IS300 Sedan"],
    "years": "1999-2005",
    "powertrain": {
      "engine_name": "2JZ-GE",
      "transmission_name": "A650E (Auto) / W55 (Manual)",
      "differential_name": "Toyota IRS"
    },
    "engine": {
      "Oil Drain Plug": 30,
      "Oil Filter": 13,
      "Valve Cover Bolts (in-lb)": 53,
      "Spark Plugs": 13,
      "Oil Capacity (qt)": 6.5,
      "Oil Type": "5W-30"
    },
    "transmission": {
      "Fluid Type": "Toyota Type T-IV",
      "Capacity (qt)": 9.0,
      "Pan Bolts (in-lb)": 69
    },
    "differential": {
      "Fluid Type": "75W-90",
      "Capacity (qt)": 1.1,
      "Drain Plug": 36,
      "Fill Plug": 36
    }
  },
  "lexus_rx350_2007_2015": {
    "models": ["RX350","RX 350","RX-350"],
    "years": "2007-2015",
    "powertrain": {
      "engine_name": "2GR-FE",
      "transmission_name": "U660E / U760F",
      "differential_name": "AWD Rear Differential"
    },
    "engine": {
      "Oil Drain Plug": 30,
      "Oil Filter": 13,
      "Spark Plugs": 13,
      "Oil Capacity (qt)": 6.4,
      "Oil Type": "0W-20"
    },
    "transmission": {
      "Fluid Type": "Toyota WS",
      "Capacity (qt)": 12.0
    },
    "differential": {
      "Fluid Type": "75W-85",
      "Capacity (qt)": 1.0
    }
  },
  "lexus_es350_2007_2018": {
    "models": ["ES350","ES 350","ES-350"],
    "years": "2007-2018",
    "powertrain": {
      "engine_name": "2GR-FE",
      "transmission_name": "U660E",
      "differential_name": "Integrated Transaxle"
    },
    "engine": {
      "Oil Drain Plug": 30,
      "Oil Filter": 13,
      "Spark Plugs": 13,
      "Oil Capacity (qt)": 6.4,
      "Oil Type": "0W-20"
    },
    "transmission": {
      "Fluid Type": "Toyota WS",
      "Capacity (qt)": 11.0
    }
  }
}
